rajdeepghosh/__init__.py
rajdeepghosh/website.py
rajdeepghosh-0.1.0.dist-info/LICENSE
rajdeepghosh-0.1.0.dist-info/METADATA
rajdeepghosh-0.1.0.dist-info/WHEEL
rajdeepghosh-0.1.0.dist-info/top_level.txt
rajdeepghosh-0.1.0.dist-info/RECORD
