Metadata-Version: 2.1
Name: rajdeepghosh
Version: 0.1.0
Summary: A package to open Rajdeep Ghosh's portfolio website
Home-page: https://github.com/rajghosh2000/rajdeepghosh
Author: Rajdeep Ghosh
Author-email: shivduttchoubey@gmail.com
Classifier: Programming Language :: Python :: 3
Classifier: License :: OSI Approved :: MIT License
Classifier: Operating System :: OS Independent
Requires-Python: >=3.6
License-File: LICENSE
